schema/__init__.py
schema/channel_types.json
schema/schema.json
schema/time_units.json
schema/__pycache__/__init__.cpython-39.pyc
snirf2bids/__init__.py
snirf2bids/__version__.py
snirf2bids/snirf2bids.py
snirf2bids-0.8.7.dist-info/LICENSE
snirf2bids-0.8.7.dist-info/METADATA
snirf2bids-0.8.7.dist-info/WHEEL
snirf2bids-0.8.7.dist-info/top_level.txt
snirf2bids-0.8.7.dist-info/RECORD
