Metadata-Version: 2.1
Name: snirf2bids
Version: 0.8.7
Summary: To convert snirf file to bids format.
Home-page: https://github.com/BUNPC/snirf2bids
Author: JC
Author-email: skura@bu.edu
License: MIT
Platform: UNKNOWN
Classifier: License :: OSI Approved :: MIT License
Classifier: Programming Language :: Python
Classifier: Programming Language :: Python :: 3
Classifier: Programming Language :: Python :: 3.6
Classifier: Programming Language :: Python :: Implementation :: CPython
Classifier: Programming Language :: Python :: Implementation :: PyPy
Requires-Python: >=3.6.0
License-File: LICENSE
Requires-Dist: numpy
Requires-Dist: setuptools
Requires-Dist: pysnirf2
Requires-Dist: importlib-resources
